hardware/decision_tree.vh
`ifndef DECISION_TREE_VH
`define DECISION_TREE_VH

localparam int NUM_NODES = 7;
localparam int FEATURE_BITS = 2;
localparam int THRESHOLD_BITS = 2;
localparam int ROW_BITS = 3;

localparam [13:0] feature_idx_packed = {2'd0, 2'd0, 2'd0, 2'd0, 2'd0, 2'd0, 2'd2};
localparam [13:0] threshold_packed = {2'd0, 2'd0, 2'd2, 2'd0, 2'd0, 2'd1, 2'd1};
localparam [20:0] left_idx_packed = {3'd0, 3'd0, 3'd5, 3'd0, 3'd0, 3'd2, 3'd1};
localparam [20:0] right_idx_packed = {3'd0, 3'd0, 3'd6, 3'd0, 3'd0, 3'd3, 3'd4};
localparam [6:0] is_leaf_packed = {1'd1, 1'd1, 1'd0, 1'd1, 1'd1, 1'd0, 1'd0};
localparam [6:0] leaf_value_packed = {1'd1, 1'd1, 1'd0, 1'd1, 1'd0, 1'd0, 1'd0};

`endif

hardware/decision_tree.sv
`include "decision_tree.vh"

module decision_tree (
    input  logic [7:0] features_packed,
    output logic       result
);

    logic [2:0] row  [0:NUM_NODES];
    logic       done [0:NUM_NODES];
    logic [1:0] cur_feature_idx;
    logic [1:0] cur_threshold;
    logic       cur_is_leaf;
    logic [1:0] this_feature_val;

    always_comb begin
        row[0]  = 3'd0;
        done[0] = 1'b0;

        for (int i = 0; i < NUM_NODES; i = i + 1) begin
            cur_feature_idx = feature_idx_packed[row[i]*2 +: 2];
            cur_threshold   = threshold_packed[row[i]*2 +: 2];
            cur_is_leaf     = is_leaf_packed[row[i]];
            this_feature_val = features_packed[cur_feature_idx*2 +: 2];

            if (done[i] || cur_is_leaf) begin
                row[i+1]  = row[i];
                done[i+1] = 1'b1;
            end else begin
                if (this_feature_val < cur_threshold)
                    row[i+1] = left_idx_packed[row[i]*3 +: 3];
                else
                    row[i+1] = right_idx_packed[row[i]*3 +: 3];
                done[i+1] = 1'b0;
            end
        end

        result = leaf_value_packed[row[NUM_NODES]];
    end

endmodule

hardware/testbench.sv
module testbench;

    logic [7:0] features_packed;
    logic       result;

    decision_tree dut (
        .features_packed(features_packed),
        .result(result)
    );

    logic [1:0] test_features [0:13][0:3];
    logic       expected_results [0:13];

    initial begin
        $dumpfile("waves.vcd");
        $dumpvars(0, testbench);

        test_features[0][0]=2'd0; test_features[0][1]=2'd0; test_features[0][2]=2'd0; test_features[0][3]=2'd0; expected_results[0]=1'd0;
        test_features[1][0]=2'd0; test_features[1][1]=2'd0; test_features[1][2]=2'd0; test_features[1][3]=2'd1; expected_results[1]=1'd0;
        test_features[2][0]=2'd1; test_features[2][1]=2'd0; test_features[2][2]=2'd0; test_features[2][3]=2'd0; expected_results[2]=1'd1;
        test_features[3][0]=2'd2; test_features[3][1]=2'd1; test_features[3][2]=2'd0; test_features[3][3]=2'd0; expected_results[3]=1'd1;
        test_features[4][0]=2'd2; test_features[4][1]=2'd2; test_features[4][2]=2'd1; test_features[4][3]=2'd0; expected_results[4]=1'd1;
        test_features[5][0]=2'd2; test_features[5][1]=2'd2; test_features[5][2]=2'd1; test_features[5][3]=2'd1; expected_results[5]=1'd1;
        test_features[6][0]=2'd1; test_features[6][1]=2'd2; test_features[6][2]=2'd1; test_features[6][3]=2'd1; expected_results[6]=1'd1;
        test_features[7][0]=2'd0; test_features[7][1]=2'd1; test_features[7][2]=2'd0; test_features[7][3]=2'd0; expected_results[7]=1'd0;
        test_features[8][0]=2'd0; test_features[8][1]=2'd2; test_features[8][2]=2'd1; test_features[8][3]=2'd0; expected_results[8]=1'd1;
        test_features[9][0]=2'd2; test_features[9][1]=2'd1; test_features[9][2]=2'd1; test_features[9][3]=2'd0; expected_results[9]=1'd1;
        test_features[10][0]=2'd0; test_features[10][1]=2'd1; test_features[10][2]=2'd1; test_features[10][3]=2'd1; expected_results[10]=1'd1;
        test_features[11][0]=2'd1; test_features[11][1]=2'd1; test_features[11][2]=2'd0; test_features[11][3]=2'd1; expected_results[11]=1'd1;
        test_features[12][0]=2'd1; test_features[12][1]=2'd0; test_features[12][2]=2'd1; test_features[12][3]=2'd0; expected_results[12]=1'd1;
        test_features[13][0]=2'd2; test_features[13][1]=2'd1; test_features[13][2]=2'd0; test_features[13][3]=2'd1; expected_results[13]=1'd1;

        for (int row = 0; row < 14; row = row + 1) begin
            features_packed = {test_features[row][3], test_features[row][2], test_features[row][1], test_features[row][0]};
            #1;
            if (result === expected_results[row])
                $display("PASS  row %0d -> %0d", row, result);
            else
                $display("FAIL  row %0d -> got %0d, expected %0d", row, result, expected_results[row]);
        end

        $finish;
    end

endmodule

hardware/waves.vcd
$date
	Mon Jul 27 18:27:06 2026
$end
$version
	Icarus Verilog
$end
$timescale
	1s
$end
$scope module testbench $end
$var wire 1 ! result $end
$var reg 8 " features_packed [7:0] $end
$scope module dut $end
$var wire 8 # features_packed [7:0] $end
$var reg 2 $ cur_feature_idx [1:0] $end
$var reg 1 % cur_is_leaf $end
$var reg 2 & cur_threshold [1:0] $end
$var reg 1 ! result $end
$var reg 2 ' this_feature_val [1:0] $end
$scope begin $ivl_for_loop0 $end
$var integer 32 ( i [31:0] $end
$upscope $end
$upscope $end
$scope begin $ivl_for_loop1 $end
$var integer 32 ) row [31:0] $end
$upscope $end
$upscope $end
$enddefinitions $end
$comment Show the parameter values. $end
$dumpall
$end
#0
$dumpvars
b0 )
b111 (
b0 '
b0 &
1%
b0 $
b0 #
b0 "
0!
$end
#1
1%
b0 &
b0 $
b111 (
b1000000 "
b1000000 #
b1 )
#2
1!
b1 '
1%
b0 &
b0 $
b111 (
b1 "
b1 #
b10 )
#3
b10 '
1%
b0 &
b0 $
b111 (
b110 "
b110 #
b11 )
#4
b10 '
1%
b0 &
b0 $
b111 (
b11010 "
b11010 #
b100 )
#5
b10 '
1%
b0 &
b0 $
b111 (
b1011010 "
b1011010 #
b101 )
#6
b1 '
1%
b0 &
b0 $
b111 (
b1011001 "
b1011001 #
b110 )
#7
0!
b0 '
1%
b0 &
b0 $
b111 (
b100 "
b100 #
b111 )
#8
1!
b0 '
1%
b0 &
b0 $
b111 (
b11000 "
b11000 #
b1000 )
#9
b10 '
1%
b0 &
b0 $
b111 (
b10110 "
b10110 #
b1001 )
#10
b0 '
1%
b0 &
b0 $
b111 (
b1010100 "
b1010100 #
b1010 )
#11
b1 '
1%
b0 &
b0 $
b111 (
b1000101 "
b1000101 #
b1011 )
#12
1%
b0 &
b0 $
b111 (
b10001 "
b10001 #
b1100 )
#13
b10 '
1%
b0 &
b0 $
b111 (
b1000110 "
b1000110 #
b1101 )
#14
b1110 )
